evm_indexer/__init__.py
evm_indexer/decoder.py
evm_indexer/fetcher.py
evm_indexer/internal_tracer.py
evm_indexer-0.0.2.dist-info/LICENSE
evm_indexer-0.0.2.dist-info/METADATA
evm_indexer-0.0.2.dist-info/WHEEL
evm_indexer-0.0.2.dist-info/top_level.txt
evm_indexer-0.0.2.dist-info/RECORD
