Metadata-Version: 2.1
Name: evm-indexer
Version: 0.0.2
Summary: EVM compatible blockchain indexer
Home-page: https://github.com/OmchainFoundation/evm-indexer
Author: Omchain Foundation
Author-email: info@omchain.io
License: LICENSE
Classifier: Development Status :: 3 - Alpha
Classifier: Intended Audience :: Developers
Classifier: Programming Language :: Python :: 3.6
Classifier: License :: OSI Approved :: MIT License
Requires-Python: >=3.6
License-File: LICENSE
Requires-Dist: web3 >=6.0.0
Requires-Dist: requests >=2.22.0
